AUTHORS.rst
CONTRIBUTING.rst
HISTORY.rst
LICENSE
MANIFEST.in
Makefile
README.rst
requirements.txt
setup.cfg
setup.py
darkskysync/AbstractRemoteSyncAdapter.py
darkskysync/DarkSkySync.py
darkskysync/DarkSkySyncCLI.py
darkskysync/DataSource.py
darkskysync/DataSourceFactory.py
darkskysync/Exceptions.py
darkskysync/LocalFileSystem.py
darkskysync/LocalSyncAdapter.py
darkskysync/RemoteFactory.py
darkskysync/RsyncWrapper.py
darkskysync/SSHClientAdapter.py
darkskysync/SSHRemoteFileSystemLocation.py
darkskysync/SSHWrapper.py
darkskysync/SshLoginInfo.py
darkskysync/__init__.py
darkskysync.egg-info/PKG-INFO
darkskysync.egg-info/SOURCES.txt
darkskysync.egg-info/dependency_links.txt
darkskysync.egg-info/entry_points.txt
darkskysync.egg-info/not-zip-safe
darkskysync.egg-info/requires.txt
darkskysync.egg-info/top_level.txt
darkskysync/data/config.template
docs/.gitignore
docs/Makefile
docs/authors.rst
docs/check_sphinx.py
docs/conf.py
docs/contributing.rst
docs/darkskysync.rst
docs/history.rst
docs/index.rst
docs/installation.rst
docs/make.bat
docs/modules.rst
docs/usage.rst
tests/ConfigHelper.py
tests/__init__.py
tests/test_ConfigReader.py
tests/test_ConfigValidator.py
tests/test_DarkSkySync.py
tests/test_DarkSkySyncCLI.py
tests/test_DataSourceFactory.py
tests/test_RsyncWrapper.py