Metadata-Version: 1.1
Name: darkskysync
Version: 0.2.0
Summary: Helps to access and synchronize with a remote data storage
Home-page: http://refreweb.phys.ethz.ch/software/darkskysync/0.1.6/
Author: Joel Akeret
Author-email: jakeret@phys.ethz.ch
License: MIT
Keywords: darkskysync
Platform: UNKNOWN
Classifier: Development Status :: 3 - Alpha
Classifier: Intended Audience :: Science/Research
Classifier: Intended Audience :: Developers
Classifier: Natural Language :: English
Classifier: Programming Language :: Python :: 2
Classifier: Programming Language :: Python :: 2.6
Classifier: Programming Language :: Python :: 2.7
